{
  "annotations": {
    "list": [
      {
        "builtIn": 1,
        "datasource": {
          "type": "datasource",
          "uid": "grafana"
        },
        "enable": true,
        "hide": true,
        "iconColor": "rgba(0, 211, 255, 1)",
        "name": "Annotations & Alerts",
        "target": {
          "limit": 100,
          "matchAny": false,
          "tags": [],
          "type": "dashboard"
        },
        "type": "dashboard"
      }
    ]
  },
  "editable": true,
  "fiscalYearStartMonth": 0,
  "graphTooltip": 0,
  "id": 2,
  "links": [],
  "panels": [
    {
      "datasource": {
        "type": "prometheus",
        "uid": "PBFA97CFB590B2093"
      },
      "fieldConfig": {
        "defaults": {
          "color": {
            "mode": "continuous-GrYlRd"
          },
          "mappings": [],
          "thresholds": {
            "mode": "absolute",
            "steps": [
              {
                "color": "green",
                "value": 0
              },
              {
                "color": "red",
                "value": 80
              }
            ]
          },
          "unit": "s"
        },
        "overrides": []
      },
      "gridPos": {
        "h": 9,
        "w": 15,
        "x": 0,
        "y": 0
      },
      "id": 6,
      "options": {
        "displayMode": "lcd",
        "legend": {
          "calcs": [],
          "displayMode": "list",
          "placement": "bottom",
          "showLegend": false
        },
        "maxVizHeight": 300,
        "minVizHeight": 10,
        "minVizWidth": 0,
        "namePlacement": "auto",
        "orientation": "horizontal",
        "reduceOptions": {
          "calcs": [
            "lastNotNull"
          ],
          "fields": "",
          "values": false
        },
        "showUnfilled": true,
        "sizing": "auto",
        "valueMode": "color"
      },
      "pluginVersion": "12.3.1",
      "targets": [
        {
          "datasource": {
            "type": "prometheus",
            "uid": "PBFA97CFB590B2093"
          },
          "editorMode": "code",
          "exemplar": false,
          "expr": "sort_desc(\r\n  (\r\n    sum by(uri) (rate(http_server_requests_seconds_sum{application=\"$app_name\", instance=\"$instance\"}[$__rate_interval]))\r\n    /\r\n    sum by(uri) (rate(http_server_requests_seconds_count{application=\"$app_name\", instance=\"$instance\"}[$__rate_interval]))\r\n  ) < 3\r\n)\r\n",
          "instant": false,
          "interval": "",
          "legendFormat": "{{method}} {{uri}}",
          "range": true,
          "refId": "A"
        }
      ],
      "title": "Fast Requests Average Duration",
      "type": "bargauge"
    },
    {
      "datasource": {
        "type": "prometheus",
        "uid": "PBFA97CFB590B2093"
      },
      "fieldConfig": {
        "defaults": {
          "color": {
            "mode": "continuous-GrYlRd"
          },
          "mappings": [],
          "thresholds": {
            "mode": "absolute",
            "steps": [
              {
                "color": "green",
                "value": 0
              },
              {
                "color": "red",
                "value": 80
              }
            ]
          },
          "unit": "s"
        },
        "overrides": []
      },
      "gridPos": {
        "h": 9,
        "w": 9,
        "x": 15,
        "y": 0
      },
      "id": 24,
      "options": {
        "displayMode": "lcd",
        "legend": {
          "calcs": [],
          "displayMode": "list",
          "placement": "bottom",
          "showLegend": false
        },
        "maxVizHeight": 300,
        "minVizHeight": 16,
        "minVizWidth": 8,
        "namePlacement": "auto",
        "orientation": "horizontal",
        "reduceOptions": {
          "calcs": [
            "lastNotNull"
          ],
          "fields": "",
          "values": false
        },
        "showUnfilled": true,
        "sizing": "auto",
        "valueMode": "color"
      },
      "pluginVersion": "12.3.1",
      "targets": [
        {
          "disableTextWrap": false,
          "editorMode": "code",
          "exemplar": false,
          "expr": "sort_desc((\r\n  sum by(uri) (rate(http_server_requests_seconds_sum{application=\"$app_name\", instance=\"$instance\",}[$__rate_interval]))\r\n  / \r\n  sum by(uri) (rate(http_server_requests_seconds_count{application=\"$app_name\", instance=\"$instance\",}[$__rate_interval]))\r\n)) >= 3",
          "fullMetaSearch": false,
          "includeNullMetadata": true,
          "instant": true,
          "legendFormat": "__auto",
          "range": false,
          "refId": "A",
          "useBackend": false
        }
      ],
      "title": "Long Requests Average Duration",
      "type": "bargauge"
    },
    {
      "datasource": {
        "type": "prometheus",
        "uid": "PBFA97CFB590B2093"
      },
      "fieldConfig": {
        "defaults": {
          "color": {
            "mode": "thresholds"
          },
          "mappings": [],
          "thresholds": {
            "mode": "absolute",
            "steps": [
              {
                "color": "green",
                "value": 0
              }
            ]
          },
          "unit": "short"
        },
        "overrides": []
      },
      "gridPos": {
        "h": 8,
        "w": 15,
        "x": 0,
        "y": 9
      },
      "id": 16,
      "options": {
        "displayMode": "gradient",
        "legend": {
          "calcs": [],
          "displayMode": "list",
          "placement": "bottom",
          "showLegend": false
        },
        "maxVizHeight": 300,
        "minVizHeight": 16,
        "minVizWidth": 8,
        "namePlacement": "auto",
        "orientation": "horizontal",
        "reduceOptions": {
          "calcs": [
            "lastNotNull"
          ],
          "fields": "",
          "values": false
        },
        "showUnfilled": true,
        "sizing": "auto",
        "valueMode": "color"
      },
      "pluginVersion": "12.3.1",
      "targets": [
        {
          "datasource": {
            "type": "prometheus",
            "uid": "PBFA97CFB590B2093"
          },
          "editorMode": "code",
          "exemplar": false,
          "expr": "sort_desc(\r\n  sum by(uri) (\r\n    increase(http_server_requests_seconds_count{application=\"$app_name\", instance=\"$instance\", uri!=\"/actuator/prometheus\", uri!=\"UNKNOWN\", uri!=\"/api/actuator/prometheus\"}[24h])\r\n  )\r\n) > 0",
          "instant": true,
          "interval": "",
          "legendFormat": "{{method}} {{uri}}",
          "range": false,
          "refId": "A"
        }
      ],
      "timeFrom": "24h",
      "title": "Requests Count",
      "transformations": [
        {
          "id": "seriesToRows",
          "options": {}
        },
        {
          "id": "sortBy",
          "options": {
            "fields": {},
            "sort": [
              {
                "field": "Time"
              }
            ]
          }
        },
        {
          "id": "partitionByValues",
          "options": {
            "fields": [
              "Metric"
            ]
          }
        }
      ],
      "type": "bargauge"
    },
    {
      "datasource": {
        "type": "prometheus",
        "uid": "PBFA97CFB590B2093"
      },
      "fieldConfig": {
        "defaults": {
          "mappings": [],
          "thresholds": {
            "mode": "absolute",
            "steps": [
              {
                "color": "green",
                "value": 0
              }
            ]
          },
          "unit": "short"
        },
        "overrides": []
      },
      "gridPos": {
        "h": 8,
        "w": 5,
        "x": 15,
        "y": 9
      },
      "id": 4,
      "options": {
        "colorMode": "value",
        "graphMode": "area",
        "justifyMode": "auto",
        "orientation": "auto",
        "percentChangeColorMode": "standard",
        "reduceOptions": {
          "calcs": [
            "lastNotNull"
          ],
          "fields": "",
          "values": false
        },
        "showPercentChange": false,
        "textMode": "auto",
        "wideLayout": true
      },
      "pluginVersion": "12.3.1",
      "targets": [
        {
          "datasource": {
            "type": "prometheus",
            "uid": "PBFA97CFB590B2093"
          },
          "editorMode": "code",
          "exemplar": false,
          "expr": "sum(increase(http_server_requests_seconds_count{application=\"$app_name\", instance=\"$instance\", uri!=\"/actuator/prometheus\", uri!=\"/api/actuator/prometheus\", uri!=\"UNKNOWN\"}[24h]))\r\n",
          "instant": true,
          "interval": "",
          "legendFormat": "",
          "range": false,
          "refId": "A"
        }
      ],
      "timeFrom": "24h",
      "title": "Total Requests",
      "transformations": [
        {
          "id": "seriesToRows",
          "options": {}
        },
        {
          "id": "sortBy",
          "options": {
            "fields": {},
            "sort": [
              {
                "field": "Time"
              }
            ]
          }
        }
      ],
      "type": "stat"
    },
    {
      "datasource": {
        "type": "prometheus",
        "uid": "PBFA97CFB590B2093"
      },
      "fieldConfig": {
        "defaults": {
          "color": {
            "mode": "thresholds"
          },
          "mappings": [],
          "thresholds": {
            "mode": "absolute",
            "steps": [
              {
                "color": "green",
                "value": 0
              },
              {
                "color": "red",
                "value": 80
              }
            ]
          }
        },
        "overrides": []
      },
      "gridPos": {
        "h": 8,
        "w": 4,
        "x": 20,
        "y": 9
      },
      "id": 22,
      "options": {
        "colorMode": "value",
        "graphMode": "area",
        "justifyMode": "auto",
        "orientation": "auto",
        "percentChangeColorMode": "standard",
        "reduceOptions": {
          "calcs": [
            "lastNotNull"
          ],
          "fields": "",
          "values": false
        },
        "showPercentChange": false,
        "textMode": "auto",
        "wideLayout": true
      },
      "pluginVersion": "12.3.1",
      "targets": [
        {
          "datasource": {
            "type": "prometheus",
            "uid": "PBFA97CFB590B2093"
          },
          "editorMode": "code",
          "exemplar": true,
          "expr": "sum(increase(http_server_requests_seconds_count{application=\"$app_name\", instance=\"$instance\", outcome=\"SERVER_ERROR\"}[24h]))\r\n",
          "interval": "",
          "legendFormat": "",
          "range": true,
          "refId": "A"
        }
      ],
      "timeFrom": "24h",
      "title": "Total Exceptions",
      "type": "stat"
    },
    {
      "datasource": {
        "type": "loki",
        "uid": "P982945308D3682D1"
      },
      "fieldConfig": {
        "defaults": {},
        "overrides": []
      },
      "gridPos": {
        "h": 9,
        "w": 18,
        "x": 0,
        "y": 17
      },
      "id": 2,
      "options": {
        "dedupStrategy": "none",
        "enableInfiniteScrolling": false,
        "enableLogDetails": true,
        "prettifyLogMessage": false,
        "showCommonLabels": false,
        "showControls": false,
        "showLabels": false,
        "showTime": false,
        "sortOrder": "Descending",
        "wrapLogMessage": true
      },
      "pluginVersion": "12.3.1",
      "targets": [
        {
          "datasource": {
            "type": "loki",
            "uid": "P982945308D3682D1"
          },
          "direction": "backward",
          "editorMode": "code",
          "expr": "{app=\"$app_name\", env=\"$env_instance\"}",
          "queryType": "range",
          "refId": "A"
        }
      ],
      "title": "Log of All Spring Boot Apps",
      "type": "logs"
    },
    {
      "datasource": {
        "type": "loki",
        "uid": "P982945308D3682D1"
      },
      "fieldConfig": {
        "defaults": {
          "color": {
            "mode": "palette-classic"
          },
          "custom": {
            "axisBorderShow": false,
            "axisCenteredZero": false,
            "axisColorMode": "text",
            "axisLabel": "",
            "axisPlacement": "auto",
            "barAlignment": 0,
            "barWidthFactor": 0.6,
            "drawStyle": "bars",
            "fillOpacity": 0,
            "gradientMode": "none",
            "hideFrom": {
              "legend": false,
              "tooltip": false,
              "viz": false
            },
            "insertNulls": false,
            "lineInterpolation": "linear",
            "lineWidth": 1,
            "pointSize": 5,
            "scaleDistribution": {
              "type": "linear"
            },
            "showPoints": "auto",
            "showValues": false,
            "spanNulls": false,
            "stacking": {
              "group": "A",
              "mode": "normal"
            },
            "thresholdsStyle": {
              "mode": "off"
            }
          },
          "mappings": [],
          "thresholds": {
            "mode": "absolute",
            "steps": [
              {
                "color": "green",
                "value": 0
              },
              {
                "color": "red",
                "value": 80
              }
            ]
          }
        },
        "overrides": [
          {
            "matcher": {
              "id": "byName",
              "options": "ERROR"
            },
            "properties": [
              {
                "id": "color",
                "value": {
                  "fixedColor": "red",
                  "mode": "fixed"
                }
              }
            ]
          },
          {
            "matcher": {
              "id": "byName",
              "options": "INFO"
            },
            "properties": [
              {
                "id": "color",
                "value": {
                  "fixedColor": "green",
                  "mode": "fixed"
                }
              }
            ]
          },
          {
            "matcher": {
              "id": "byName",
              "options": "CRITICAL"
            },
            "properties": [
              {
                "id": "color",
                "value": {
                  "fixedColor": "purple",
                  "mode": "fixed"
                }
              }
            ]
          },
          {
            "matcher": {
              "id": "byName",
              "options": "{level=\"INFO\"}"
            },
            "properties": [
              {
                "id": "color",
                "value": {
                  "fixedColor": "green",
                  "mode": "fixed"
                }
              }
            ]
          },
          {
            "matcher": {
              "id": "byName",
              "options": "{level=\"ERROR\"}"
            },
            "properties": [
              {
                "id": "color",
                "value": {
                  "fixedColor": "red",
                  "mode": "fixed"
                }
              }
            ]
          },
          {
            "matcher": {
              "id": "byName",
              "options": "{level=\"DEBUG\"}"
            },
            "properties": [
              {
                "id": "color",
                "value": {
                  "fixedColor": "blue",
                  "mode": "fixed"
                }
              }
            ]
          },
          {
            "matcher": {
              "id": "byName",
              "options": "{level=\"WARN\"}"
            },
            "properties": [
              {
                "id": "color",
                "value": {
                  "fixedColor": "yellow",
                  "mode": "fixed"
                }
              }
            ]
          }
        ]
      },
      "gridPos": {
        "h": 9,
        "w": 6,
        "x": 18,
        "y": 17
      },
      "id": 14,
      "options": {
        "legend": {
          "calcs": [],
          "displayMode": "list",
          "placement": "bottom",
          "showLegend": true
        },
        "tooltip": {
          "hideZeros": false,
          "mode": "single",
          "sort": "none"
        }
      },
      "pluginVersion": "12.3.1",
      "targets": [
        {
          "datasource": {
            "type": "loki",
            "uid": "P982945308D3682D1"
          },
          "direction": "backward",
          "editorMode": "code",
          "expr": "sum by(level) (rate({app=\"$app_name\",  env=\"$env_instance\"} | pattern `<date> <time> <_>=<trace_id> <_>=<span_id> <_>=<trace_flags> <type> <_> --- <msg>` |= \"$log_keyword\" [1m]))\n",
          "queryType": "range",
          "refId": "A"
        }
      ],
      "title": "Log Type Rate",
      "type": "timeseries"
    },
    {
      "datasource": {
        "type": "prometheus",
        "uid": "PBFA97CFB590B2093"
      },
      "fieldConfig": {
        "defaults": {
          "color": {
            "mode": "palette-classic"
          },
          "custom": {
            "axisBorderShow": false,
            "axisCenteredZero": false,
            "axisColorMode": "text",
            "axisLabel": "",
            "axisPlacement": "auto",
            "barAlignment": 0,
            "barWidthFactor": 0.6,
            "drawStyle": "line",
            "fillOpacity": 0,
            "gradientMode": "none",
            "hideFrom": {
              "legend": false,
              "tooltip": false,
              "viz": false
            },
            "insertNulls": false,
            "lineInterpolation": "linear",
            "lineWidth": 1,
            "pointSize": 5,
            "scaleDistribution": {
              "type": "linear"
            },
            "showPoints": "auto",
            "showValues": false,
            "spanNulls": false,
            "stacking": {
              "group": "A",
              "mode": "none"
            },
            "thresholdsStyle": {
              "mode": "off"
            }
          },
          "mappings": [],
          "thresholds": {
            "mode": "absolute",
            "steps": [
              {
                "color": "green",
                "value": 0
              },
              {
                "color": "red",
                "value": 80
              }
            ]
          },
          "unit": "reqps"
        },
        "overrides": []
      },
      "gridPos": {
        "h": 14,
        "w": 12,
        "x": 0,
        "y": 26
      },
      "id": 12,
      "options": {
        "legend": {
          "calcs": [],
          "displayMode": "list",
          "placement": "bottom",
          "showLegend": true
        },
        "tooltip": {
          "hideZeros": false,
          "mode": "single",
          "sort": "none"
        }
      },
      "pluginVersion": "12.3.1",
      "targets": [
        {
          "datasource": {
            "type": "prometheus",
            "uid": "PBFA97CFB590B2093"
          },
          "editorMode": "code",
          "expr": "sum by(uri)(rate(http_server_requests_seconds_count{application=\"$app_name\", instance=\"$instance\", uri!=\"/api/actuator/prometheus\", uri!=\"UNKNOWN\"}[1m]))",
          "range": true,
          "refId": "A"
        }
      ],
      "title": "Request Per Sec",
      "type": "timeseries"
    },
    {
      "datasource": {
        "type": "prometheus",
        "uid": "PBFA97CFB590B2093"
      },
      "fieldConfig": {
        "defaults": {
          "color": {
            "mode": "palette-classic"
          },
          "custom": {
            "axisBorderShow": false,
            "axisCenteredZero": false,
            "axisColorMode": "text",
            "axisLabel": "",
            "axisPlacement": "auto",
            "axisSoftMax": 1,
            "barAlignment": 0,
            "barWidthFactor": 0.6,
            "drawStyle": "line",
            "fillOpacity": 0,
            "gradientMode": "none",
            "hideFrom": {
              "legend": false,
              "tooltip": false,
              "viz": false
            },
            "insertNulls": false,
            "lineInterpolation": "linear",
            "lineWidth": 1,
            "pointSize": 5,
            "scaleDistribution": {
              "type": "linear"
            },
            "showPoints": "auto",
            "showValues": false,
            "spanNulls": false,
            "stacking": {
              "group": "A",
              "mode": "none"
            },
            "thresholdsStyle": {
              "mode": "area"
            }
          },
          "mappings": [],
          "thresholds": {
            "mode": "absolute",
            "steps": [
              {
                "color": "red",
                "value": 0
              },
              {
                "color": "green",
                "value": 0.8
              }
            ]
          },
          "unit": "percentunit"
        },
        "overrides": []
      },
      "gridPos": {
        "h": 7,
        "w": 12,
        "x": 12,
        "y": 26
      },
      "id": 18,
      "options": {
        "legend": {
          "calcs": [],
          "displayMode": "list",
          "placement": "bottom",
          "showLegend": true
        },
        "tooltip": {
          "hideZeros": false,
          "mode": "single",
          "sort": "none"
        }
      },
      "pluginVersion": "12.3.1",
      "targets": [
        {
          "datasource": {
            "type": "prometheus",
            "uid": "PBFA97CFB590B2093"
          },
          "editorMode": "code",
          "exemplar": true,
          "expr": "sum by(uri) (http_server_requests_seconds_count{application=\"$app_name\", instance=\"$instance\", status=~\"2.*\", uri!=\"/actuator/prometheus\"}) / sum by(uri) (http_server_requests_seconds_count{application=\"$app_name\", uri!=\"/api/actuator/prometheus\"})",
          "interval": "",
          "legendFormat": "{{path}}",
          "range": true,
          "refId": "A"
        }
      ],
      "title": "Percent of 2xx Requests",
      "type": "timeseries"
    },
    {
      "datasource": {
        "type": "prometheus",
        "uid": "PBFA97CFB590B2093"
      },
      "fieldConfig": {
        "defaults": {
          "color": {
            "mode": "palette-classic"
          },
          "custom": {
            "axisBorderShow": false,
            "axisCenteredZero": false,
            "axisColorMode": "text",
            "axisLabel": "",
            "axisPlacement": "auto",
            "axisSoftMax": 1,
            "barAlignment": 0,
            "barWidthFactor": 0.6,
            "drawStyle": "line",
            "fillOpacity": 0,
            "gradientMode": "none",
            "hideFrom": {
              "legend": false,
              "tooltip": false,
              "viz": false
            },
            "insertNulls": false,
            "lineInterpolation": "linear",
            "lineWidth": 1,
            "pointSize": 5,
            "scaleDistribution": {
              "type": "linear"
            },
            "showPoints": "auto",
            "showValues": false,
            "spanNulls": false,
            "stacking": {
              "group": "A",
              "mode": "none"
            },
            "thresholdsStyle": {
              "mode": "area"
            }
          },
          "mappings": [],
          "thresholds": {
            "mode": "absolute",
            "steps": [
              {
                "color": "green",
                "value": 0
              },
              {
                "color": "red",
                "value": 0.1
              }
            ]
          },
          "unit": "percentunit"
        },
        "overrides": []
      },
      "gridPos": {
        "h": 7,
        "w": 12,
        "x": 12,
        "y": 33
      },
      "id": 20,
      "options": {
        "legend": {
          "calcs": [],
          "displayMode": "list",
          "placement": "bottom",
          "showLegend": true
        },
        "tooltip": {
          "hideZeros": false,
          "mode": "single",
          "sort": "none"
        }
      },
      "pluginVersion": "12.3.1",
      "targets": [
        {
          "datasource": {
            "type": "prometheus",
            "uid": "PBFA97CFB590B2093"
          },
          "editorMode": "code",
          "exemplar": true,
          "expr": "sum by(uri) (http_server_requests_seconds_count{application=\"$app_name\", instance=\"$instance\", status=~\"5.*\", uri!=\"/actuator/prometheus\"}) / sum by(uri) (http_server_requests_seconds_count{application=\"$app_name\", uri!=\"/actuator/prometheus\"})",
          "interval": "",
          "legendFormat": "{{uri}}",
          "range": true,
          "refId": "A"
        }
      ],
      "title": "Percent of 5xx Requests",
      "type": "timeseries"
    },
    {
      "datasource": {
        "type": "prometheus",
        "uid": "PBFA97CFB590B2093"
      },
      "fieldConfig": {
        "defaults": {
          "color": {
            "mode": "palette-classic"
          },
          "custom": {
            "axisBorderShow": false,
            "axisCenteredZero": false,
            "axisColorMode": "text",
            "axisLabel": "",
            "axisPlacement": "auto",
            "barAlignment": 0,
            "barWidthFactor": 0.6,
            "drawStyle": "line",
            "fillOpacity": 0,
            "gradientMode": "none",
            "hideFrom": {
              "legend": false,
              "tooltip": false,
              "viz": false
            },
            "insertNulls": false,
            "lineInterpolation": "linear",
            "lineWidth": 1,
            "pointSize": 5,
            "scaleDistribution": {
              "type": "linear"
            },
            "showPoints": "auto",
            "showValues": false,
            "spanNulls": false,
            "stacking": {
              "group": "A",
              "mode": "none"
            },
            "thresholdsStyle": {
              "mode": "off"
            }
          },
          "mappings": [],
          "thresholds": {
            "mode": "absolute",
            "steps": [
              {
                "color": "green",
                "value": 0
              },
              {
                "color": "red",
                "value": 80
              }
            ]
          },
          "unit": "s"
        },
        "overrides": []
      },
      "gridPos": {
        "h": 13,
        "w": 11,
        "x": 0,
        "y": 40
      },
      "id": 8,
      "options": {
        "legend": {
          "calcs": [],
          "displayMode": "list",
          "placement": "bottom",
          "showLegend": true
        },
        "tooltip": {
          "hideZeros": false,
          "mode": "single",
          "sort": "none"
        }
      },
      "pluginVersion": "12.3.1",
      "targets": [
        {
          "datasource": {
            "type": "prometheus",
            "uid": "PBFA97CFB590B2093"
          },
          "editorMode": "code",
          "exemplar": true,
          "expr": "histogram_quantile(0.99, sum(rate(http_server_requests_seconds_bucket{application=\"$app_name\", instance=\"$instance\", uri!=\"/api/actuator/prometheus\", uri!=\"UNKNOWN\"}[30m])) by (uri, le))\r\n",
          "interval": "",
          "legendFormat": "{{uri}}",
          "range": true,
          "refId": "A"
        }
      ],
      "title": "PR 99 Requests Duration",
      "type": "timeseries"
    },
    {
      "datasource": {
        "type": "prometheus",
        "uid": "PBFA97CFB590B2093"
      },
      "fieldConfig": {
        "defaults": {
          "color": {
            "mode": "palette-classic"
          },
          "custom": {
            "axisBorderShow": false,
            "axisCenteredZero": false,
            "axisColorMode": "text",
            "axisLabel": "",
            "axisPlacement": "auto",
            "barAlignment": 0,
            "barWidthFactor": 0.6,
            "drawStyle": "line",
            "fillOpacity": 0,
            "gradientMode": "none",
            "hideFrom": {
              "legend": false,
              "tooltip": false,
              "viz": false
            },
            "insertNulls": false,
            "lineInterpolation": "linear",
            "lineWidth": 1,
            "pointSize": 5,
            "scaleDistribution": {
              "type": "linear"
            },
            "showPoints": "auto",
            "showValues": false,
            "spanNulls": false,
            "stacking": {
              "group": "A",
              "mode": "none"
            },
            "thresholdsStyle": {
              "mode": "off"
            }
          },
          "mappings": [],
          "thresholds": {
            "mode": "absolute",
            "steps": [
              {
                "color": "green",
                "value": 0
              },
              {
                "color": "red",
                "value": 80
              }
            ]
          },
          "unit": "s"
        },
        "overrides": []
      },
      "gridPos": {
        "h": 13,
        "w": 13,
        "x": 11,
        "y": 40
      },
      "id": 23,
      "options": {
        "legend": {
          "calcs": [],
          "displayMode": "list",
          "placement": "bottom",
          "showLegend": true
        },
        "tooltip": {
          "hideZeros": false,
          "mode": "single",
          "sort": "none"
        }
      },
      "pluginVersion": "12.3.1",
      "targets": [
        {
          "datasource": {
            "type": "prometheus",
            "uid": "PBFA97CFB590B2093"
          },
          "editorMode": "code",
          "exemplar": true,
          "expr": "histogram_quantile(.95,sum(rate(http_server_requests_seconds_bucket{application=\"$app_name\", instance=\"$instance\", uri!=\"/api/actuator/prometheus\", uri!=\"UNKNOWN\"}[30m])) by(uri, le))",
          "interval": "",
          "legendFormat": "{{uri}}",
          "range": true,
          "refId": "A"
        }
      ],
      "title": "PR 95 Requests Duration",
      "type": "timeseries"
    }
  ],
  "preload": false,
  "refresh": "15m",
  "schemaVersion": 42,
  "tags": [],
  "templating": {
    "list": [
      {
        "current": {
          "text": "gps-guide-api",
          "value": "gps-guide-api"
        },
        "datasource": {
          "type": "prometheus",
          "uid": "PBFA97CFB590B2093"
        },
        "definition": "label_values(application)",
        "includeAll": false,
        "label": "Application Name",
        "name": "app_name",
        "options": [],
        "query": {
          "query": "label_values(application)",
          "refId": "StandardVariableQuery"
        },
        "refresh": 1,
        "regex": "",
        "type": "query"
      },
      {
        "current": {
          "text": "",
          "value": ""
        },
        "description": "query with keyword",
        "label": "Log Query",
        "name": "log_keyword",
        "options": [
          {
            "selected": true,
            "text": "",
            "value": ""
          }
        ],
        "query": "",
        "type": "textbox"
      },
      {
        "baseFilters": [],
        "datasource": {
          "type": "loki",
          "uid": "aemnelm2o2waoa"
        },
        "filters": [],
        "name": "Filters",
        "type": "adhoc"
      },
      {
        "current": {
          "text": "10.20.17.25:8080",
          "value": "10.20.17.25:8080"
        },
        "definition": "label_values({application=\"$app_name\"},instance)",
        "label": "Application instance",
        "name": "instance",
        "options": [],
        "query": {
          "qryType": 1,
          "query": "label_values({application=\"$app_name\"},instance)",
          "refId": "PrometheusVariableQueryEditor-VariableQuery"
        },
        "refresh": 1,
        "regex": "",
        "type": "query"
      },
      {
        "current": {
          "text": "test",
          "value": "test"
        },
        "definition": "label_values({instance=\"$instance\"},instance_type)",
        "hide": 2,
        "name": "env_instance",
        "options": [],
        "query": {
          "qryType": 1,
          "query": "label_values({instance=\"$instance\"},instance_type)",
          "refId": "PrometheusVariableQueryEditor-VariableQuery"
        },
        "refresh": 1,
        "regex": "",
        "type": "query"
      }
    ]
  },
  "time": {
    "from": "now-5m",
    "to": "now"
  },
  "timepicker": {},
  "timezone": "",
  "title": "Spring Boot Observability",
  "uid": "dLsDQIUnzb",
  "version": 2
}